README.md
setup.cfg
setup.py
inspire_service_orcid/__init__.py
inspire_service_orcid/client.py
inspire_service_orcid/conf.py
inspire_service_orcid/exceptions.py
inspire_service_orcid/hooks.py
inspire_service_orcid/models.py
inspire_service_orcid/utils.py
inspire_service_orcid.egg-info/PKG-INFO
inspire_service_orcid.egg-info/SOURCES.txt
inspire_service_orcid.egg-info/dependency_links.txt
inspire_service_orcid.egg-info/not-zip-safe
inspire_service_orcid.egg-info/requires.txt
inspire_service_orcid.egg-info/top_level.txt